arrayLSTM/__init__.py
arrayLSTM/arraylstm.py
arrayLSTM/lstm.py
arrayLSTM/extensions/__init__.py
arrayLSTM/extensions/attention.py
arrayLSTM/extensions/stochastic.py
array_lstm-0.0.1.dist-info/LICENSE
array_lstm-0.0.1.dist-info/METADATA
array_lstm-0.0.1.dist-info/WHEEL
array_lstm-0.0.1.dist-info/top_level.txt
array_lstm-0.0.1.dist-info/RECORD
