Metadata-Version: 2.1
Name: array-lstm
Version: 0.0.1
Summary: Pytorch implementation of Recurrent Memory Array Structures
Home-page: https://github.com/Thijsvanede/ArrayLSTM
Author: Thijs van Ede
Author-email: t.s.vanede@utwente.nl
License: UNKNOWN
Platform: UNKNOWN
Classifier: Programming Language :: Python :: 3
Classifier: License :: OSI Approved :: MIT License
Classifier: Operating System :: OS Independent
